distawareaug/__init__.py
distawareaug/augmentor.py
distawareaug/config.py
distawareaug/distance.py
distawareaug/distribution.py
distawareaug/py.typed
distawareaug/utils.py
distawareaug-0.2.0.dist-info/licenses/LICENSE
distawareaug-0.2.0.dist-info/METADATA
distawareaug-0.2.0.dist-info/WHEEL
distawareaug-0.2.0.dist-info/top_level.txt
distawareaug-0.2.0.dist-info/RECORD
