Metadata-Version: 2.4
Name: distawareaug
Version: 0.2.0
Summary: Distribution-Aware Data Augmentation for Imbalanced Learning
Author-email: Atunrase Ayo <atunraseayomide@gmail.com>
Maintainer-email: Atunrase Ayo <atunraseayomide@gmail.com>
License: MIT
Project-URL: Homepage, https://github.com/Ayo-Cyber/DistAwareAug
Project-URL: Documentation, https://github.com/Ayo-Cyber/DistAwareAug#readme
Project-URL: Repository, https://github.com/Ayo-Cyber/DistAwareAug
Project-URL: Issues, https://github.com/Ayo-Cyber/DistAwareAug/issues
Project-URL: Changelog, https://github.com/Ayo-Cyber/DistAwareAug/releases
Keywords: machine-learning,imbalanced-learning,data-augmentation,oversampling,smote,distribution-fitting,synthetic-data
Classifier: Development Status :: 3 - Alpha
Classifier: Intended Audience :: Developers
Classifier: Intended Audience :: Science/Research
Classifier: License :: OSI Approved :: MIT License
Classifier: Operating System :: OS Independent
Classifier: Programming Language :: Python :: 3
Classifier: Programming Language :: Python :: 3.8
Classifier: Programming Language :: Python :: 3.9
Classifier: Programming Language :: Python :: 3.10
Classifier: Programming Language :: Python :: 3.11
Classifier: Programming Language :: Python :: 3.12
Classifier: Topic :: Scientific/Engineering :: Artificial Intelligence
Classifier: Topic :: Software Development :: Libraries :: Python Modules
Requires-Python: >=3.8
License-File: LICENSE
Requires-Dist: numpy>=1.21.0
Requires-Dist: pandas>=1.3.0
Requires-Dist: scikit-learn>=1.0.0
Requires-Dist: scipy>=1.7.0
Requires-Dist: matplotlib>=3.4.0
Requires-Dist: seaborn>=0.11.0
Requires-Dist: statsmodels>=0.13.0
Provides-Extra: dev
Requires-Dist: pytest>=7.0.0; extra == "dev"
Requires-Dist: pytest-cov>=4.0.0; extra == "dev"
Requires-Dist: black>=22.0.0; extra == "dev"
Requires-Dist: isort>=5.10.0; extra == "dev"
Requires-Dist: flake8>=4.0.0; extra == "dev"
Requires-Dist: mypy>=0.950; extra == "dev"
Requires-Dist: pre-commit>=2.17.0; extra == "dev"
Provides-Extra: docs
Requires-Dist: sphinx>=4.5.0; extra == "docs"
Requires-Dist: sphinx-rtd-theme>=1.0.0; extra == "docs"
Requires-Dist: sphinx-autodoc-typehints>=1.18.0; extra == "docs"
Provides-Extra: examples
Requires-Dist: jupyter>=1.0.0; extra == "examples"
Requires-Dist: notebook>=6.4.0; extra == "examples"
Requires-Dist: imbalanced-learn>=0.10.0; extra == "examples"
Provides-Extra: all
Requires-Dist: distawareaug[dev,docs,examples]; extra == "all"
Dynamic: license-file
